odoo9_addon_l10n_ma_state-9.0.0.1.0-py2.7-nspkg.pth
odoo_addons/l10n_ma_state/__openerp__.py
odoo_addons/l10n_ma_state/__init__.py
odoo_addons/l10n_ma_state/README.rst
odoo_addons/l10n_ma_state/data/res_country_state_data.yml
odoo_addons/l10n_ma_state/static/description/icon.png
odoo_addons/l10n_ma_state/static/src/img/screenshots/1.png
odoo9_addon_l10n_ma_state-9.0.0.1.0.dist-info/top_level.txt
odoo9_addon_l10n_ma_state-9.0.0.1.0.dist-info/WHEEL
odoo9_addon_l10n_ma_state-9.0.0.1.0.dist-info/RECORD
odoo9_addon_l10n_ma_state-9.0.0.1.0.dist-info/metadata.json
odoo9_addon_l10n_ma_state-9.0.0.1.0.dist-info/DESCRIPTION.rst
odoo9_addon_l10n_ma_state-9.0.0.1.0.dist-info/METADATA
odoo9_addon_l10n_ma_state-9.0.0.1.0.dist-info/namespace_packages.txt
